opentelemetry/instrumentation/haystack/__init__.py
opentelemetry/instrumentation/haystack/config.py
opentelemetry/instrumentation/haystack/utils.py
opentelemetry/instrumentation/haystack/version.py
opentelemetry/instrumentation/haystack/wrap_node.py
opentelemetry/instrumentation/haystack/wrap_openai.py
opentelemetry/instrumentation/haystack/wrap_pipeline.py
opentelemetry_if_instrumentation_haystack-0.25.6.dist-info/METADATA
opentelemetry_if_instrumentation_haystack-0.25.6.dist-info/WHEEL
opentelemetry_if_instrumentation_haystack-0.25.6.dist-info/entry_points.txt
opentelemetry_if_instrumentation_haystack-0.25.6.dist-info/RECORD
