Metadata-Version: 2.3
Name: opentelemetry-if-instrumentation-haystack
Version: 0.25.6
Summary: OpenTelemetry Haystack instrumentation
Home-page: https://github.com/traceloop/openllmetry/tree/main/packages/opentelemetry-instrumentation-haystack
License: Apache-2.0
Author: Gal Kleinman
Author-email: gal@traceloop.com
Requires-Python: >=3.9,<4
Classifier: License :: OSI Approved :: Apache Software License
Classifier: Programming Language :: Python :: 3
Classifier: Programming Language :: Python :: 3.9
Classifier: Programming Language :: Python :: 3.10
Classifier: Programming Language :: Python :: 3.11
Classifier: Programming Language :: Python :: 3.12
Classifier: Programming Language :: Python :: 3.13
Provides-Extra: instruments
Requires-Dist: opentelemetry-api (>=1.25.0,<2.0.0)
Requires-Dist: opentelemetry-if-semantic-conventions-ai (==0.3.6)
Requires-Dist: opentelemetry-instrumentation (>=0.46b0,<0.47)
Requires-Dist: opentelemetry-semantic-conventions (>=0.46b0,<0.47)
Project-URL: Repository, https://github.com/traceloop/openllmetry/tree/main/packages/opentelemetry-instrumentation-haystack
